socio4health/__init__.py
socio4health/__main__.py
socio4health/extractor.py
socio4health/harmonizer.py
socio4health/enums/__init__.py
socio4health/enums/data_info_enum.py
socio4health/enums/dict_enum.py
socio4health/utils/__init__.py
socio4health/utils/extractor_utils.py
socio4health/utils/harmonizer_utils.py
socio4health/utils/standard_spider.py
socio4health-1.0.0.dist-info/licenses/LICENSE.md
socio4health-1.0.0.dist-info/METADATA
socio4health-1.0.0.dist-info/WHEEL
socio4health-1.0.0.dist-info/entry_points.txt
socio4health-1.0.0.dist-info/top_level.txt
socio4health-1.0.0.dist-info/RECORD
