Metadata-Version: 2.4
Name: socio4health
Version: 1.0.0
Summary: Socio4health is a Python package for gathering and consolidating socio-demographic data.
Home-page: https://github.com/harmonize-tools/socio4health
Author: Erick Lozano, Diego Irreño, Juan Montenegro, Ingrid Mora
Author-email: 
Project-URL: Bug Reports, https://github.com/harmonize-tools/socio4health/issues
Project-URL: Source, https://github.com/harmonize-tools/socio4health/
Project-URL: Changelog, https://github.com/harmonize-tools/socio4health/blob/main/CHANGELOG.md
Keywords: extract transform load etl scraping relational census sociodemographic colombia brazil
Classifier: Development Status :: 2 - Pre-Alpha
Classifier: Intended Audience :: Developers
Classifier: Topic :: Software Development :: Build Tools
Classifier: License :: OSI Approved :: MIT License
Classifier: Programming Language :: Python :: 3
Classifier: Programming Language :: Python :: 3.10
Classifier: Programming Language :: Python :: 3.11
Classifier: Programming Language :: Python :: 3.12
Classifier: Programming Language :: Python :: 3.13
Classifier: Programming Language :: Python :: 3 :: Only
Requires-Python: >=3.10, <4
License-File: LICENSE.md
Requires-Dist: pandas>=2.0.0
Requires-Dist: requests>=2.31.0
Requires-Dist: Scrapy>=2.11.1
Requires-Dist: tqdm>=4.66.1
Requires-Dist: pyreadstat>=1.2.6
Requires-Dist: py7zr>=0.20.8
Requires-Dist: matplotlib>=3.7.0
Requires-Dist: numpy>=1.24.0
Requires-Dist: openpyxl>=3.1.2
Requires-Dist: dask>=2023.0.0
Requires-Dist: appdirs>=1.4.4
Requires-Dist: pyarrow>=12.0.0
Requires-Dist: deep-translator>=1.11.4
Requires-Dist: transformers>=4.30.0
Requires-Dist: torch>=2.0.0
Requires-Dist: geopandas>=0.14.0
Provides-Extra: dev
Requires-Dist: check-manifest; extra == "dev"
Requires-Dist: pytest; extra == "dev"
Provides-Extra: test
Requires-Dist: coverage; extra == "test"
Dynamic: author
Dynamic: classifier
Dynamic: description
Dynamic: description-content-type
Dynamic: home-page
Dynamic: keywords
Dynamic: license-file
Dynamic: project-url
Dynamic: provides-extra
Dynamic: requires-dist
Dynamic: requires-python
Dynamic: summary
